jewish_library/__init__.py
jewish_library/demo.py
jewish_library/server.py
jewish_library/tantivy_search_agent.py
mseep_jewish_library-0.1.4.dist-info/licenses/LICENSE
mseep_jewish_library-0.1.4.dist-info/METADATA
mseep_jewish_library-0.1.4.dist-info/WHEEL
mseep_jewish_library-0.1.4.dist-info/entry_points.txt
mseep_jewish_library-0.1.4.dist-info/top_level.txt
mseep_jewish_library-0.1.4.dist-info/RECORD
