Metadata-Version: 2.4
Name: mseep-jewish_library
Version: 0.1.4
Summary: the jewish library, accessible to LLMs 
Author-email: mseep <support@skydeck.ai>
Requires-Python: >=3.10
License-File: LICENSE
Requires-Dist: mcp>=1.1.1
Requires-Dist: tantivy
Dynamic: license-file
